wi/__init__.py
wi/main.py
wi/controllers/__init__.py
wi/controllers/base.py
wi/controllers/groups.py
wi/controllers/secrets.py
wi/core/__init__.py
wi/core/exc.py
wi/core/version.py
wi/ext/__init__.py
wi/plugins/__init__.py
wi/templates/__init__.py
wi/templates/command1.jinja2
wi/templates/secrets/list.jinja2
wi_cli-0.0.1.dev20220908025727.dist-info/LICENSE.md
wi_cli-0.0.1.dev20220908025727.dist-info/METADATA
wi_cli-0.0.1.dev20220908025727.dist-info/WHEEL
wi_cli-0.0.1.dev20220908025727.dist-info/entry_points.txt
wi_cli-0.0.1.dev20220908025727.dist-info/top_level.txt
wi_cli-0.0.1.dev20220908025727.dist-info/RECORD
