Metadata-Version: 2.1
Name: wi-cli
Version: 0.0.1.dev20220908025727
Summary: Wi will allow storing and using a set of environment variables based on current directory
Home-page: https://github.com/BrentGruber/wi/
Author: Brent Gruber
Author-email: me@brentgruber.net
License: unlicensed
License-File: LICENSE.md
